<msbt attribsize="8">
	<message label="001" attrib="00 00 00 00 00 00 00 00">Ce feu d'artifice est magique, <anim id="ShyBoy" target="actor" targetSpec="" />je suis
si captivée que j'ai dû mettre des
gouttes pour m'hydrater les yeux.</message>
	<message label="002" attrib="00 00 00 00 00 00 00 00">À chaque BOUM que j'entends,<delay8 /><anim id="Clapping" target="actor" targetSpec="" />
j'imagine que c'est le ciel qui me
fait une ovation, <tag a="110" b="6" />.<delay frames="40" /><anim id="FaintSmile" target="actor" targetSpec="" /></message>
	<message label="003" attrib="00 00 00 00 00 00 00 00"><anim id="Clapping" target="actor" targetSpec="" />J'imagine même pas la forme des
prochains feux d'artifice !<delay20 /><anim id="QuestionMark" target="actor" targetSpec="" /> Tu crois
qu'il y aura des fleurs ?<delay20 /> Des cœurs ?!
Sérieux,<anim id="Smiling" target="actor" targetSpec="" /> même en forme <gender4 m="de " f="d'⁠" /><tag a="135" b="7" arg="0xcd00" /> ou <gender4 m="de " f="d'⁠" /><tag a="135" b="5" arg="0xcd00" />, je serais heureuse.</message>
	<message label="004" attrib="00 00 00 00 00 00 00 00"><anim id="HappyDance" target="actor" targetSpec="" />Je sais pas d'où ça vient, mais les
feux d'artifice <gender4 m="de " f="d'⁠" /><tag a="110" b="8" /> sont toujours au-dessus du lot.<pageBreak /><anim id="SmugFace" target="actor" targetSpec="" />Cette île doit être un aimant à ce qui
se fait de meilleur, <tag a="110" b="6" />.</message>
	<message label="005" attrib="00 00 00 00 00 00 00 00"><anim id="Pardon" target="actor" targetSpec="" />OooOOoh !<delay frames="40" /><anim id="Explain" target="actor" targetSpec="" /> Tu les vois, les énormes
fleurs qui éclosent dans le ciel ?<pageBreak /><anim id="HappyFlower" target="actor" targetSpec="" />Et le plus fou, c'est que ces fleurs,<delay8 />
elles sont faites EN FEU !<delay frames="40" /><anim id="Serious" target="actor" targetSpec="" /> Tu vois le
délire, <tag a="110" b="6" /> ?</message>
	<message label="006" attrib="00 00 00 00 00 00 00 00"><anim id="Hesitate" target="actor" targetSpec="" />J'ai toujours rêvé de voir mon nom
écrit en lettres de feu.<delay8 /> Alors je me
demandais<tag a="110" b="0" /><pageBreak />Ça serait pas incroyable, si le feu
d'artifice écrivait <anim id="EmotEnd" target="actor" targetSpec="" />« ⁠<tag a="110" b="10" /> ⁠» dans le ciel ?</message>
	<message label="007" attrib="00 00 00 00 00 00 00 00"><anim id="Aha" target="actor" targetSpec="" />Écoute un peu !<delay20 /> <anim id="Explain" target="actor" targetSpec="" />Ces grosses fusées,<delay8 />
les énormes qui viennent d'exploser
à l'instant, <tag a="110" b="6" /><tag a="110" b="0" /><pageBreak /><anim id="HappyDance" target="actor" targetSpec="" />J'aurai les mêmes à mon premier
concert<tag a="110" b="0" /><delay20 /><anim id="EmotEnd" target="actor" targetSpec="" /> juste après mon deuxième
rappel, <tag a="110" b="6" /> !</message>
	<message label="008" attrib="00 00 00 00 00 00 00 00"><anim id="Thinking" target="actor" targetSpec="" />Comment ils font pour lancer des
fusées aussi haut et obtenir des
formes pareilles, <tag a="110" b="6" /> ?
En tant qu'artiste,<anim id="Nodding" target="actor" targetSpec="" /> je me dois de
m'intéresser au travail de mes
confrères.</message>
	<message label="009" attrib="00 00 00 00 00 00 00 00"><anim id="Sighing" target="actor" targetSpec="" />Bouh !<delay8 /> Le feu d'artifice est presque terminé, <tag a="110" b="6" />.<pageBreak /><anim id="AbsentMindedness" target="actor" targetSpec="" />Si tu me vois regarder,<delay8 /> songeuse,<delay8 /> les
dernières étincelles qui s'éteignent<tag a="110" b="0" /><pageBreak /><anim id="Nodding" target="actor" targetSpec="" />Prends vite une photo.<delay frames="40" /> <anim id="SmugFace" target="actor" targetSpec="" />Un jour
viendra où tu me demanderas de
te la signer.</message>
	<message label="010" attrib="00 00 00 00 00 00 00 00"><anim id="Oops" target="actor" targetSpec="" />J'en reviens pas que le feu d'artifice
soit bientôt fini, <tag a="110" b="6" />.<pageBreak />Si on applaudit assez fort, <anim id="QuestionMark" target="actor" targetSpec="" />on aura
droit à un rappel, <tag a="110" b="6" /> ?</message>
	<message label="011" attrib="00 00 00 00 00 00 00 00"><anim id="Pardon" target="actor" targetSpec="" />Wouah !<delay20 /> Tu l'as vue, celle-là ?<delay40 /> <anim id="WrySmile" target="actor" targetSpec="" />Elle
était tellement grosse que j'en ai les
larmes aux yeux.
<anim id="Crying" target="actor" targetSpec="" />OK.<delay8 /> Je vais pas te mentir.<delay20 /> Je pleure.<delay20 />
<anim id="FaintSmile" target="actor" targetSpec="" />Mais c'est des larmes de joie devant
ce chouette feu d'artifice, c'est tout.</message>
</msbt>