<msbt attribsize="8">
	<message label="001" attrib="00 00 00 00 00 00 00 00"><anim id="Aha" target="actor" targetSpec="" />Oh, ciao! <delay frames="40" /><anim id="QuestionMark" target="actor" targetSpec="" />Sei qui per la mia
megafesta di compleanno,
<tag a="110" b="5" />?</message>
	<message label="002" attrib="00 00 00 00 00 00 00 00"><anim id="Hello" target="actor" targetSpec="" />Sei arrivat<gender2 m="o" f="a" />, <tag a="110" b="3" />!<delay frames="40" />
<anim id="Grin" target="actor" targetSpec="" />Sarà una festa indimenticabile!</message>
	<message label="003" attrib="00 00 00 00 00 00 00 00"><anim id="Greeting" target="actor" targetSpec="" />Ehi, <tag a="110" b="3" />! <delay20 />Ce l'hai
fatta!<delay frames="40" /> <anim id="Nodding" target="actor" targetSpec="" />Stiamo appena iniziando,
<delay frames="40" /><anim id="Hello" target="actor" targetSpec="" />preparati a ballare tutta la notte!</message>
	<message label="004" attrib="00 00 02 00 00 00 00 00"><anim id="FaintSmile" target="actor" targetSpec="" />Un compleanno è un'ottima scusa
per fare una festa con tanta gente!
<delay frames="40" /><anim id="Eh" target="actor" targetSpec="" />Mi hanno persino portato regali!
<anim id="Aha" target="actor" targetSpec="" />Oh, ehm<tag a="110" b="0" /><delay8 /><anim id="Hesitate" target="actor" targetSpec="" /> Non è che per caso hai
portato anche tu qualcosa?</message>
	<message label="004_a" attrib="00 00 00 00 00 00 00 00">Ma certo!</message>
	<message label="004_b" attrib="00 00 00 00 00 00 00 00">No, mi dispiace...</message>
	<message label="005" attrib="00 00 02 00 00 00 00 00"><anim id="Smiling" target="actor" targetSpec="" />Averti qui per la mia festa non mi
dispiace affatto, <tag a="110" b="5" />.<pageBreak /><anim id="ShyBoy" target="actor" targetSpec="" />Non voglio sembrarti scortese, ma<tag a="110" b="0" />
<delay8 />mi hai per caso portato un regalo?</message>
	<message label="005_a" attrib="00 00 00 00 00 00 00 00">Eccolo!</message>
	<message label="005_b" attrib="00 00 00 00 00 00 00 00"><anim id="EmotEnd" target="player" targetSpec="" />Ehm... no, spiacente.</message>
	<message label="006" attrib="00 00 02 00 00 00 00 00"><anim id="Smiling" target="actor" targetSpec="" />Questa sì che è una bella festa. <delay frames="40" />
E tutto grazie agli amici presenti.<pageBreak /><anim id="Hesitate" target="actor" targetSpec="" />A proposito di presenti<tag a="110" b="0" /> Non è che
mi hai portato un regalo?</message>
	<message label="006_a" attrib="00 00 00 00 00 00 00 00">Certamente!</message>
	<message label="006_b" attrib="00 00 00 00 00 00 00 00">Ups... no.</message>
	<message label="007" attrib="00 00 00 00 00 00 00 00"><anim id="Shocked" target="actor" targetSpec="" />Va bene, non fa niente.<delay frames="40" /><anim id="Grin" target="actor" targetSpec="" /> Non ti farò
certo pagare il cibo che consumi,
<tag a="110" b="5" />!<pageBreak /><anim id="ShyBoy" target="actor" targetSpec="" />Però c'è ancora tempo<tag a="110" b="0" /> nel caso
cambi idea e volessi regalarmi
qualcosa.</message>
	<message label="008" attrib="00 00 00 00 00 00 00 00"><anim id="BrokenHeart" target="actor" targetSpec="" />Come puoi spezzarmi il cuore così?<delay40 />
<anim id="Laughing" target="actor" targetSpec="" />Ah ah ah! <delay20 />Stavo scherzando! <delay20 />La tua
faccia è stata il più bel regalo!
<anim id="FaintSmile" target="actor" targetSpec="" />Lo so, il mio senso dell'umorismo è
abbastanza<tag a="110" b="0" /> particolare. <delay frames="40" />Ora buttati
nella mischia e divertiti!</message>
	<message label="009" attrib="00 00 00 00 00 00 00 00"><anim id="Oops" target="actor" targetSpec="" />Ah, beh, <delay20 />non volevo metterti
in imbarazzo, <tag a="110" b="5" />.<pageBreak /><anim id="Nodding" target="actor" targetSpec="" />Mi piacciono le persone che non
cercano di compiacerti a tutti i costi.
<delay frames="40" /><anim id="Smiling" target="actor" targetSpec="" />E ora, pensa solo alla festa!</message>
	<message label="010" attrib="00 00 00 00 00 00 00 00"><anim id="Shocked" target="actor" targetSpec="" />Ehi, credo di non averti mai vist<gender2 m="o" f="a" />
prima. <delay frames="40" /><anim id="SmugFace" target="actor" targetSpec="" />Ho ragione, eh? <delay20 />Come al
solito! <delay20 />Io sono <tag a="110" b="10" />.
<anim id="Greeting" target="actor" targetSpec="" />Benvenut<gender2 m="o" f="a" /> alla mia festa!
<delay frames="40" /><anim id="Laughing" target="actor" targetSpec="" /><gender2 m="Un nuovo amico" f="Una nuova amica" /> è un regalo
di compleanno<tag a="110" b="0" /> insolito!</message>
	<message label="011" attrib="00 00 00 00 00 00 00 00"><anim id="Eh" target="actor" targetSpec="" />Eh?<delay frames="40" /> <anim id="QuestionMark" target="actor" targetSpec="" />Hai dimenticato il regalo a casa?</message>
	<message label="014" attrib="00 00 00 00 00 00 00 00"><anim id="FaintSmile" target="actor" targetSpec="" />Lo hai persino incartato! <delay20 /><anim id="ShyBoy" target="actor" targetSpec="" />Mi dispiace
quasi disfare tutto il tuo lavoro<tag a="110" b="0" />
ma sono troppo curiosa!</message>
	<message label="015" attrib="00 00 00 00 00 00 00 00"><anim id="Thinking" target="actor" targetSpec="" />Se il regalo è bello quanto la
confezione<tag a="110" b="0" /><anim id="Laughing" target="actor" targetSpec="" /> Dovrò fingere di
compiere gli anni più spesso!</message>
	<message label="016" attrib="00 00 00 00 00 00 00 00"><anim id="OhGeez" target="actor" targetSpec="" />Non sopporto le persone curiose,<delay8 />
<anim id="FaintSmile" target="actor" targetSpec="" />ma di fronte a un regalo incartato,
mi trasformo in una di loro.</message>
	<message label="017" attrib="00 00 00 00 00 00 00 00"><anim id="Aha" target="actor" targetSpec="" />Non pensavo che fossi il tipo da
regalare dolci!<delay frames="40" /><anim id="Laughing" target="actor" targetSpec="" /> Hai appena
guadagnato un paio di punti!</message>
	<message label="018" attrib="00 00 00 00 00 00 00 00"><anim id="Laughing" target="actor" targetSpec="" /><tag a="50" b="3" /><tag a="50" b="2" /><tag a="125" b="0" arg="0x0" />?
<delay frames="40" />Conosci bene i miei gusti. <delay20 />Ne
ho comprat<tag a="50" b="17" arg="0x12 0xcd00 0x2 0x6f 0x2 0x61 0x0" /> un<tag a="50" b="17" arg="0x12 0xcd00 0x2 0x6f 0x2 0x61 0x0" /> giusto ieri!
<anim id="FaintSmile" target="actor" targetSpec="" />Terrò il tuo regalo e mi libererò
del mio doppione!</message>
	<message label="019" attrib="00 00 00 00 00 00 00 00"><anim id="QuestionMark" target="actor" targetSpec="" /><tag a="50" b="3" /><tag a="50" b="2" /><tag a="125" b="0" arg="0x0" />!? <delay frames="40" /><anim id="Laughing" target="actor" targetSpec="" />Ah ah ah! <delay20 />Non hai visto che indosso esattamente lo stesso articolo?<pageBreak /><anim id="Nodding" target="actor" targetSpec="" />Bene, adesso ne ho un<tag a="50" b="17" arg="0x12 0xcd00 0x2 0x6f 0x2 0x61 0x0" /> di ricambio,
per quando faccio il bucato.<delay frames="40" />
<anim id="FaintSmile" target="actor" targetSpec="" />Beh, che dire? Ehm<tag a="110" b="0" /> grazie.</message>
	<message label="020" attrib="00 00 00 00 00 00 00 00"><anim id="QuestionMark" target="actor" targetSpec="" /><tag a="50" b="3" /><tag a="125" b="0" arg="0x0" />?
<delay frames="40" /><anim id="IdeaBulb" target="actor" targetSpec="" />Aspetta un attimo! <delay8 />Non ce l'hai
addosso anche tu?
<anim id="Explain" target="actor" targetSpec="" />A te non sta male. <delay20 />Spero che faccia
fare bella figura anche a me.
<delay frames="40" /><anim id="Laughing" target="actor" targetSpec="" />Dovremmo indossarl<tag a="50" b="17" arg="0x12 0xcd00 0x2 0x6f 0x2 0x61 0x0" /> insieme!</message>
	<message label="021" attrib="00 00 00 00 00 00 00 00"><anim id="Aha" target="actor" targetSpec="" />Accidenti! <delay8 />Mi regali davvero <tag a="50" b="2" /><tag a="125" b="0" arg="0x0" />?!<delay frames="40" /> <anim id="Assent" target="actor" targetSpec="" />I tuoi gusti non sono niente male.<pageBreak /><anim id="Greeting" target="actor" targetSpec="" />Mi dovrei vergognare ad accettare
un regalo così costoso! <delay20 /><anim id="WrySmile" target="actor" targetSpec="" />Dovrei<tag a="110" b="0" />
<delay8 />ma non lo faccio!</message>
	<message label="022" attrib="00 00 00 00 00 00 00 00"><anim id="Aha" target="actor" targetSpec="" />Hai davvero deciso di regalarmi
<tag a="50" b="2" /><tag a="125" b="0" arg="0x0" />?!<pageBreak /><anim id="Laughing" target="actor" targetSpec="" />Che generosità! <delay20 /><anim id="Nodding" target="actor" targetSpec="" />Non mi dimenticherò
facilmente del tuo regalo!</message>
	<message label="023" attrib="00 00 00 00 00 00 00 00"><anim id="Greeting" target="actor" targetSpec="" /><tag a="50" b="3" /><tag a="50" b="2" /><tag a="125" b="0" arg="0x0" />!<delay frames="40" />
<anim id="FaintSmile" target="actor" targetSpec="" />Non mi dispiacciono queste tue idee.</message>
	<message label="024" attrib="00 00 00 00 00 00 00 00"><anim id="TakenAback" target="actor" targetSpec="" />Era da un po' che volevo comprare <tag a="50" b="1" /><tag a="125" b="0" arg="0x0" />!<delay frames="40" /> <anim id="WrySmile" target="actor" targetSpec="" />Ehm<tag a="110" b="0" /> insomma<tag a="110" b="0" /> grazie.</message>
	<message label="025" attrib="00 00 00 00 00 00 00 00"><anim id="FaintSmile" target="actor" targetSpec="" /><tag a="50" b="3" /><tag a="50" b="2" /><tag a="125" b="0" arg="0x0" />!
Niente male.</message>
	<message label="026" attrib="00 00 00 00 00 00 00 00"><anim id="FaintSmile" target="actor" targetSpec="" /><tag a="50" b="3" /><tag a="50" b="2" /><tag a="125" b="0" arg="0x0" />!<delay20 />
<anim id="Nodding" target="actor" targetSpec="" />Mi tornerà utile.</message>
	<message label="027" attrib="00 00 00 00 00 00 00 00"><anim id="TakenAback" target="actor" targetSpec="" />Eh? <delay8 />Stelline? <delay frames="40" /><anim id="Confused" target="actor" targetSpec="" />So che è difficile
trovare il regalo giusto, ma non
posso accettarle.
<anim id="Nodding" target="actor" targetSpec="" />Apprezzo comunque il pensiero.</message>
	<message label="028" attrib="00 00 00 00 00 00 00 00"><anim id="Shocked" target="actor" targetSpec="" />Rifiuti!? <delay frames="40" /><anim id="Laughing" target="actor" targetSpec="" />Ah ah ah! Bello scherzo,
ci sono quasi cascata! Ah ah ah!<pageBreak /><anim id="Shocked" target="actor" targetSpec="" />Come? <delay8 />Non è uno scherzo? <delay8 /><anim id="Surprised" target="actor" targetSpec="" />Vuoi
darmi davvero della spazzatura come
regalo di compleanno?</message>
	<message label="029" attrib="00 00 00 00 00 00 00 00"><anim id="Aha" target="actor" targetSpec="" />Diciamo che mi aspettavo di tutto,
tranne che<tag a="110" b="0" /> delle rape.<pageBreak /><anim id="Nodding" target="actor" targetSpec="" />Hanno un aspetto appetitoso, però.
Dici che posso mangiarle?</message>
	<message label="030" attrib="00 00 00 00 00 00 00 00"><anim id="Aha" target="actor" targetSpec="" /><tag a="50" b="3" /><tag a="50" b="2" /><tag a="125" b="0" arg="0x0" />!<delay frames="40" />
<anim id="FaintSmile" target="actor" targetSpec="" />Mi sembrava di aver sentito odore
di cibo<tag a="110" b="0" /></message>
	<message label="031" attrib="00 00 00 00 00 00 00 00"><anim id="Shocked" target="actor" targetSpec="" />Uau! <delay20 />Uno schema fai da te per
<tag a="50" b="2" /><tag a="125" b="0" arg="0x0" />?!<pageBreak /><anim id="BigSmile" target="actor" targetSpec="" />È davvero <delay20 />troppo bello!<pageBreak /><anim id="Worried" target="actor" targetSpec="" />Già<tag a="110" b="0" /><delay20 /> fin troppo, a dire il vero.<delay frames="40" /> <anim id="Negative" target="actor" targetSpec="" />Non
posso accettarlo. <delay20 />Questi schemi mica
crescono sugli alberi. <delay20 />Tienilo tu.<pageBreak /><anim id="Nodding" target="actor" targetSpec="" />Dopotutto è il pensiero che conta,
e tu <delay20 />hai dato <delay20 />del tuo meglio!<delay frames="40" /> <anim id="Grin" target="actor" targetSpec="" />Sei
veramente grande, <tag a="110" b="5" />.</message>
	<message label="048" attrib="00 00 00 00 00 00 00 00"><anim id="ShyBoy" target="actor" targetSpec="" />Ho una cosina per ricambiare:
<tag a="50" b="2" /><tag a="125" b="4" arg="0x0" />.<pageBreak /><anim id="ShyBoy" target="actor" targetSpec="" />Non è granché, ma in fin dei conti
è il mio compleanno, <delay8 />non il tuo.</message>
	<message label="049" attrib="00 00 00 00 00 00 00 00"><anim id="WrySmile" target="actor" targetSpec="" />Ho preso anch'io qualcosa
per te. <delay20 />Così vuole l'etichetta,
da queste parti.</message>
	<message label="050" attrib="00 00 00 00 00 00 00 00"><anim id="Nodding" target="actor" targetSpec="" />Non è per niente male, <delay8 />averti qui
alla mia festa. <anim id="HappyDance" target="actor" targetSpec="" /><delay20 />E ora scusami, devo
scatenarmi!</message>
	<message label="051" attrib="00 00 00 00 00 00 00 00"><anim id="Hesitate" target="actor" targetSpec="" />Beh<tag a="110" b="0" /> insomma<tag a="110" b="0" /> allora mi tocca
ringraziarti.</message>
	<message label="052" attrib="00 00 00 00 00 00 00 00"><anim id="Greeting" target="actor" targetSpec="" />Beh, sappi che il tuo regalo non mi è
dispiaciuto per niente, <tag a="110" b="6" />!</message>
	<message label="054" attrib="00 00 00 00 00 00 00 00"><anim id="Laughing" target="actor" targetSpec="" />Non sono ancora così vecchia, se
riesco ancora a fare festa tutta la
notte, giusto?</message>
	<message label="055" attrib="00 00 00 00 00 00 00 00"><anim id="Clapping" target="actor" targetSpec="" />Forza, tutti a ballare e divertirsi!
<anim id="Grin" target="actor" targetSpec="" />Voglio una festa indimenticabile!</message>
	<message label="056" attrib="00 00 00 00 00 00 00 00"><anim id="Hesitate" target="actor" targetSpec="" />È incredibile come alla propria festa
non si trova mai il tempo di mangiare
una fetta di torta in pace!</message>
	<message label="057" attrib="00 00 00 00 00 00 00 00"><anim id="SmugFace" target="actor" targetSpec="" />Vale la pena invecchiare, per
organizzare una festa del genere!</message>
	<message label="058" attrib="00 00 00 00 00 00 00 00"><anim id="QuestionMark" target="actor" targetSpec="" />Sai cos'è il bello del fare gli anni,
<tag a="110" b="5" />?<pageBreak /><anim id="Explain" target="actor" targetSpec="" />Comincia un anno nuovo<tag a="110" b="0" /> ma
non serve fare improbabili buoni
propositi, <tag a="110" b="6" />.</message>
	<message label="060" attrib="00 00 02 00 00 00 00 00"><anim id="Hesitate" target="actor" targetSpec="" />Il compleanno sarebbe ancora meglio
se ricevessi un regalo da parte tua<tag a="110" b="0" /><delay8 />
<anim id="Pardon" target="actor" targetSpec="" />Capita la sottile allusione?</message>
	<message label="060_a" attrib="00 00 00 00 00 00 00 00">Capita! Ecco qui!</message>
	<message label="060_b" attrib="00 00 00 00 00 00 00 00">No, troppo sottile...</message>
	<message label="061" attrib="00 00 02 00 00 00 00 00"><anim id="Serious" target="actor" targetSpec="" />I regali che ho ricevuto non erano
male!<delay frames="40" /> <anim id="Grin" target="actor" targetSpec="" />Chissà come sarà il tuo,
<tag a="110" b="5" /><tag a="110" b="0" /></message>
	<message label="061_a" attrib="00 00 00 00 00 00 00 00"><anim id="EmotEnd" target="actor" targetSpec="" />Guarda pure!</message>
	<message label="061_b" attrib="00 00 00 00 00 00 00 00"><anim id="EmotEnd" target="actor" targetSpec="" />Ehm... il mio?</message>
	<message label="062" attrib="00 00 02 00 00 00 00 00"><anim id="AbsentMindedness" target="actor" targetSpec="" />È valsa la pena organizzare questa
festa<tag a="110" b="0" /><anim id="Eh" target="actor" targetSpec="" /> Guarda che torta, che
divertimento, che regali!
<anim id="Hesitate" target="actor" targetSpec="" />Ehm, e tu<tag a="110" b="0" /> Non volevi forse darmi
qualcosa, <tag a="110" b="5" />?</message>
	<message label="062_a" attrib="00 00 00 00 00 00 00 00"><anim id="EmotEnd" target="actor" targetSpec="" />Io? Certo, un regalo!</message>
	<message label="062_b" attrib="00 00 00 00 00 00 00 00"><anim id="EmotEnd" target="actor" targetSpec="" />I miei auguri!</message>
	<message label="064" attrib="00 00 00 00 00 00 00 00"><anim id="QuestionMark" target="actor" targetSpec="" />Te ne vai di già?<delay frames="40" /><anim id="FaintSmile" target="actor" targetSpec="" /> La festa sta appena
cominciando a scaldarsi!<pageBreak /><anim id="Greeting" target="actor" targetSpec="" />Capisco, hai impegni. Allora<tag a="110" b="0" /> ehm<tag a="110" b="0" />
insomma<tag a="110" b="0" /> grazie della presenza e
del regalo.</message>
	<message label="065" attrib="00 00 00 00 00 00 00 00"><anim id="Eh" target="actor" targetSpec="" />Vai già a casa? <delay frames="40" /><anim id="Hello" target="actor" targetSpec="" />Oh, ehm<tag a="110" b="0" /> non
è stato male averti qui e anche
per il regalo<tag a="110" b="0" /> beh, grazie.
<anim id="Laughing" target="actor" targetSpec="" />Certo, potevi anche rimanere
un altro po', <tag a="110" b="6" />!</message>
	<message label="066" attrib="00 00 00 00 00 00 00 00"><anim id="QuestionMark" target="actor" targetSpec="" />Devi proprio andartene? <delay frames="40" /><anim id="Nodding" target="actor" targetSpec="" />Beh, la tua
presenza alla festa è stata<tag a="110" b="0" /> ehm<tag a="110" b="0" />
niente male. <delay frames="40" /><anim id="Greeting" target="actor" targetSpec="" />E neanche il tuo regalo!</message>
	<message label="067" attrib="00 00 00 00 00 00 00 00"><anim id="Angry" target="actor" targetSpec="" />Ehi! <delay8 />Dove credi di andare?<pageBreak /><anim id="Laughing" target="actor" targetSpec="" />Ah ah, non ti preoccupare, non ti
posso mica costringere a restare
con la forza!</message>
	<message label="068" attrib="00 00 00 00 00 00 00 00"><anim id="SadSpiral" target="actor" targetSpec="" />Peccato che te ne stia già andando,
<tag a="110" b="6" />.</message>
	<message label="069" attrib="00 00 00 00 00 00 00 00"><anim id="Aha" target="actor" targetSpec="" />Aspetta! Devo fare gli onori di casa,
prima che te ne vada!<pageBreak /><anim id="Restless" target="actor" targetSpec="" />Allora<tag a="110" b="0" /> eh<tag a="110" b="0" /> <delay frames="40" />gr-<delay8 />gr-<delay8 />grazie di essere
venut<gender2 m="o" f="a" /> alla mia festa, <tag a="110" b="5" />.</message>
	<message label="071" attrib="00 00 00 00 00 00 00 00"><anim id="Eh" target="actor" targetSpec="" />Oh!<delay20 /> Che si dice, <tag a="110" b="3" />?<delay frames="40" /> <anim id="FaintSmile" target="actor" targetSpec="" />Non mi dispiace incontrarti, finalmente!<pageBreak /><anim id="Smiling" target="actor" targetSpec="" />Stare qui <tag a="50" b="15" /> <tag a="110" b="33" /> non è niente male, sai?<pageBreak /><anim id="Scheming" target="actor" targetSpec="" />A proposito, <delay20 />ho una notiziona<tag a="110" b="0" /><delay40 />
<anim id="BigSmile" target="actor" targetSpec="" />È IL MIO COMPLEANNO!<pageBreak /><anim id="ShyBoy" target="actor" targetSpec="" />Quindi ti tocca restare, <delay8 />divertirti
e trascorrere del tempo con i miei
amici!<delay20 /> Pover<gender2 m="o" f="a" /> te!<delay frames="40" /> <anim id="Laughing" target="actor" targetSpec="" />Gah ah ah!</message>
	<message label="072" attrib="00 00 00 00 00 00 00 00"><anim id="Hello" target="actor" targetSpec="" />Ehi, che storia, <tag a="110" b="3" />!<delay frames="40" />
<anim id="Smiling" target="actor" targetSpec="" />Non mi aspettavo di incontrarti qui,
<tag a="110" b="5" />!
<anim id="Serious" target="actor" targetSpec="" />Che c'è di nuovo, eh?! <delay20 />Mh<tag a="110" b="0" /><delay20 />
<anim id="Explain" target="actor" targetSpec="" />Beh, <delay20 />la vita non è niente male
<tag a="50" b="15" /> <tag a="110" b="8" />!<pageBreak /><anim id="Nodding" target="actor" targetSpec="" />Ho buoni amici, <delay20 />mi diverto, <delay20 />non
mi stanco troppo. <delay frames="40" />Oh, eeeee<tag a="110" b="0" /><delay20 />
<anim id="BigSmile" target="actor" targetSpec="" />OGGI È IL MIO COMPLEANNO!
<anim id="Grin" target="actor" targetSpec="" />Come vedi, degli amici hanno
conciato casa mia<tag a="110" b="0" /> per la festa.<delay frames="40" />
<anim id="Laughing" target="actor" targetSpec="" />Gah ah ah!</message>
	<message label="073" attrib="00 00 00 00 00 00 00 00"><anim id="Eh" target="actor" targetSpec="" />Oh! <delay20 />Non credo di averti mai vist<gender2 m="o" f="a" /> qui in giro. <anim id="Hello" target="actor" targetSpec="" />Io sono <tag a="110" b="10" />. <delay20 />Piacere, <tag a="110" b="5" />.<pageBreak /><anim id="Explain" target="actor" targetSpec="" />Sei arrivat<gender2 m="o" f="a" /> proprio al momento
giusto. <delay20 />Cosa intendo?<10_4 /> <anim id="HappyFlower" target="actor" targetSpec="" />È<delay20 /> IL MIO<delay20 />
COMPLEANNO,<delay frames="40" /> ecco cosa intendo!
<anim id="Smiling" target="actor" targetSpec="" />Comunque sia, sì, naturalmente c'è
una festa! <delay20 />Se vuoi, puoi restare.<delay frames="40" />
<anim id="Grin" target="actor" targetSpec="" />E, credimi, <delay20 />tu vuoi restare.</message>
	<message label="080" attrib="00 00 00 00 00 00 00 00"><anim id="Grin" target="actor" targetSpec="" />Hai fatto tutta questa strada per
venire fin qui da un'altra isola e mi
hai addirittura portato un regalo?<pageBreak /><anim id="BigSmile" target="actor" targetSpec="" />Beh, non ho parole.<pageBreak /><anim id="Nodding" target="actor" targetSpec="" />Ti darò una cosina, sì, giusto per
ringraziarti<tag a="110" b="0" /> <delay frames="40" /><anim id="Serious" target="actor" targetSpec="" />Ah! <delay20 />Ma hai le tasche
piene, adesso.<pageBreak /><anim id="Smiling" target="actor" targetSpec="" />Non importa. <delay20 />Non mi allontanerò da
qui.<delay20 /> Ripassa prima di partire, quando
avrai spazio, <tag a="110" b="6" />!</message>
	<message label="081" attrib="00 00 00 00 00 00 00 00"><anim id="Aha" target="actor" targetSpec="" /><delay20 />Oh, <tag a="110" b="3" />!<delay20 /> Si direbbe
che adesso tu sia più legger<gender2 m="o" f="a" />,
<tag a="110" b="5" />.<pageBreak /><anim id="Smiling" target="actor" targetSpec="" />Ecco il mio regalo per ringraziarti.
<delay20 />È <tag a="50" b="2" /><tag a="125" b="4" arg="0x0" />!</message>
	<message label="100" attrib="00 00 02 00 00 00 00 00"><anim id="FaintSmile" target="actor" targetSpec="" />Lo sai che <tag a="115" b="1" arg="0xcd00" /> e io facciamo gli anni lo stesso giorno? <delay20 /><anim id="Nodding" target="actor" targetSpec="" />Incredibile, vero?<pageBreak /><anim id="Nodding" target="actor" targetSpec="" />Questo vuol dire doppia torta,
doppia festa, doppio tutto.<pageBreak /><anim id="Explain" target="actor" targetSpec="" />E sai cosa mi farebbe doppiamente
contenta? <anim id="Pardon" target="actor" targetSpec="" />Avere un regalo da parte
tua, <tag a="110" b="6" />.</message>
	<message label="100_a" attrib="00 00 00 00 00 00 00 00"><anim id="EmotEnd" target="actor" targetSpec="" />Giusto, ecco qui!</message>
	<message label="100_b" attrib="00 00 00 00 00 00 00 00"><anim id="EmotEnd" target="actor" targetSpec="" />Scusa, non ho niente.</message>
</msbt>