<msbt attribsize="8">
	<message label="001" attrib="00 00 00 00 00 00 00 00"><anim id="Smiling" target="actor" targetSpec="" />がんばってるぅ～？<delay frames="40" />
ボクだって　まけないからねぇ～、<tag a="110" b="6" /></message>
	<message label="002" attrib="00 00 00 00 00 00 00 00"><anim id="QuestionMark" target="actor" targetSpec="" />ちょうしは　どう～？<delay frames="40" />
<anim id="Confused" target="actor" targetSpec="" />いそがないと<delay8 />
<ruby a="4" b="8">たいかい</ruby>大会がおわっちゃうよぉ～、<tag a="110" b="6" /></message>
	<message label="003" attrib="00 00 00 00 00 00 00 00"><anim id="Frantic" target="actor" targetSpec="" />おしゃべりしてたら<delay20 />
ムシさん　にげちゃうよぉ～？　<tag a="110" b="6" /></message>
	<message label="004" attrib="00 00 00 00 00 00 00 00"><ruby a="4" b="6">きょう</ruby>今日は　ボクも　<ruby a="4" b="6">ほんき</ruby>本気だからねぇ～<delay frames="40" />
<anim id="Serious" target="actor" targetSpec="" />キミには　まけないよぉ～！　<tag a="110" b="6" /></message>
	<message label="005" attrib="00 00 00 00 00 00 00 00"><anim id="QuestionMark" target="actor" targetSpec="" />おしゃべりしてて　だいじょうぶぅ？<delay40 />
おサカナ　にげちゃうよぉ～？　<tag a="110" b="6" /></message>
	<message label="006" attrib="00 00 00 00 00 00 00 00"><anim id="Frantic" target="actor" targetSpec="" />いそがないと<delay20 />
<ruby a="4" b="6">じかん</ruby>時間が　なくなっちゃうよぉ～？　<tag a="110" b="6" /></message>
</msbt>