<msbt attribsize="8">
	<message label="001" attrib="00 00 00 00 00 00 00 00"><anim id="Shocked" target="actor" targetSpec="" />Hast du schon gehört?<pageBreak /><anim id="OhGeez" target="actor" targetSpec="" /><tag a="115" b="1" arg="0xcd00" /> hat sich eingefangen, <delay8 />was gerade auf <tag a="110" b="8" /> umgeht.<pageBreak /><anim id="Nodding" target="actor" targetSpec="" /><tag a="50" b="17" arg="0xe 0xcd00 0x4 0x45 0x72 0x6 0x53 0x69 0x65 0x0" /> würde es bestimmt zu schätzen
wissen, <delay8 />wenn du <tag a="50" b="17" arg="0xe 0xcd00 0x6 0x69 0x68 0x6d 0x6 0x69 0x68 0x72 0x0" /> einen kurzen
Besuch abstatten würdest.</message>
	<message label="002" attrib="00 00 00 00 00 00 00 00"><anim id="Worried" target="actor" targetSpec="" />Du liebe Zeit... <delay20 />Ich befürchte,<delay8 /> <tag a="115" b="1" arg="0xcd00" /> geht es gerade gar nicht gut.<pageBreak /><anim id="Thinking" target="actor" targetSpec="" />Ich fühle mich immer besser, <delay8 />wenn
ein Freund da ist, <delay8 />also besuche
<tag a="50" b="17" arg="0xe 0xcd00 0x6 0x69 0x68 0x6e 0x6 0x73 0x69 0x65 0x0" /> doch einfach einmal.</message>
	<message label="003" attrib="00 00 00 00 00 00 00 00"><anim id="Worried" target="actor" targetSpec="" />Ich habe gehört, <delay8 />dass es <tag a="115" b="1" arg="0xcd00" /> gerade nicht so gut geht.<pageBreak /><anim id="Serious" target="actor" targetSpec="" />Wenn du etwas <colour id="1" />Medizin<colour id="65535" /> hättest,<delay8 />
wüsste <tag a="50" b="17" arg="0xe 0xcd00 0x4 0x65 0x72 0x6 0x73 0x69 0x65 0x0" /> das sicher zu schätzen...</message>
</msbt>