<msbt attribsize="8">
	<message label="999" attrib="00 00 00 00 00 00 00 00">这间屋子里放着的<delay20 />
全都是<tag a="110" b="4" /><delay20 />
<anim id="QuestionMark" target="actor" targetSpec="" />喜欢的东西吧？<delay frames="40" />
<20_2 arg="10" /><anim id="Thinking" target="actor" targetSpec="" /><tag a="125" b="0" arg="0x0" /><20_2 arg="9" /><tag a="110" b="0" /><delay frames="40" />
<anim id="EmotEnd" target="actor" targetSpec="" />嘻嘻～<delay20 /><anim id="Grin" target="actor" targetSpec="" />看来<tag a="110" b="4" />还有<delay20 />
我不知道的另一面呢～<pageBreak /><20_3 arg="6" /><20_3 arg="3" /><anim id="Nodding" target="actor" targetSpec="" />就让我仔细看看你的房间，<delay20 />
更加全面地<delay20 />
<anim id="Greeting" target="actor" targetSpec="" />了解一下你吧～！<tag a="110" b="6" />。</message>
	<message label="001" attrib="00 00 00 00 00 00 00 00"><20_2 arg="10" /><anim id="Eh" target="actor" targetSpec="" /><20_2 arg="9" /><tag a="125" b="0" arg="0x0" />，<delay20 />
是用<tag a="110" b="32" />上长的蘑菇制作的吗？！<pageBreak /><20_3 arg="6" /><20_3 arg="3" /><anim id="HappyDance" target="actor" targetSpec="" />哇～<delay20 />只靠<tag a="110" b="32" />上有的材料，
竟然能做出这样的东西，<delay20 />
你真是无人岛生活的达人呢～<tag a="110" b="6" />。</message>
	<message label="002" attrib="00 00 00 00 00 00 00 00"><20_2 arg="10" /><20_2 arg="9" /><tag a="125" b="0" arg="0x0" />，<delay20 />
一直没有化掉呢～<pageBreak /><20_3 arg="6" /><20_3 arg="3" /><anim id="Frantic" target="actor" targetSpec="" />我还一直在想，<delay frames="40" />
<anim id="EmotEnd" target="actor" targetSpec="" />如果它在家里化掉，那可就太糟糕了。<delay20 />
<anim id="Laughing" target="actor" targetSpec="" />看来是白担心了呀～<tag a="110" b="6" />。<anim id="FaintSmile" target="actor" targetSpec="" /></message>
	<message label="003" attrib="00 00 00 00 00 00 00 00"><20_2 arg="10" /><anim id="Nodding" target="actor" targetSpec="" /><20_2 arg="9" /><tag a="125" b="0" arg="0x0" />这类家具，<delay8 />
只要摆在房间里，<delay20 />
就能让房间风格一下子变成和风～<pageBreak /><20_3 arg="6" /><20_3 arg="3" />已经不单单是给人成熟的感觉，<delay20 />
<anim id="Laughing" target="actor" targetSpec="" />而是成熟过了头，
快要变成老爷爷了。<tag a="110" b="6" />。<anim id="FaintSmile" target="actor" targetSpec="" /></message>
	<message label="004" attrib="00 00 00 00 00 00 00 00"><20_2 arg="10" /><anim id="Smiling" target="actor" targetSpec="" /><delay20 /><20_2 arg="9" /><tag a="125" b="0" arg="0x0" /><delay20 />
是用积木搭出来的吗～？<pageBreak /><20_3 arg="6" /><20_3 arg="3" /><anim id="HappyDance" target="actor" targetSpec="" />如果一间房间里<delay8 />
放满了用积木搭出来的家具，<delay20 />
感觉就像一个大大的玩具箱～<tag a="110" b="6" />。</message>
	<message label="005" attrib="00 00 00 00 00 00 00 00"><anim id="Explain" target="actor" targetSpec="" />很久很久以前制作的东西，<delay20 />
放到现在<delay20 />就叫做“古董”，<delay8 />对不对～？<pageBreak /><20_2 arg="10" /><20_2 arg="9" />这么古老的东西能够一直流传至今，<delay20 />
<tag a="125" b="0" arg="0x0" /><delay20 />
<anim id="Nodding" target="actor" targetSpec="" />应该很被人珍视吧～<tag a="110" b="6" />。</message>
	<message label="006" attrib="00 00 00 00 00 00 00 00"><20_2 arg="10" /><anim id="Smiling" target="actor" targetSpec="" /><20_2 arg="9" />看到这个<tag a="125" b="0" arg="0x0" /><delay20 />
就让我回想起了校园生活呢～<pageBreak /><20_3 arg="6" /><20_3 arg="3" /><anim id="Laughing" target="actor" targetSpec="" />印象最深刻的当然就是学校的午餐～！<delay frames="50" />
<anim id="EmotEnd" target="actor" targetSpec="" />如果有人请假，<delay20 />多出来的布丁大家就会用猜拳
来决定归谁，<anim id="Scheming" target="actor" targetSpec="" />我每次都会参加哦～<tag a="110" b="6" />。</message>
	<message label="007" attrib="00 00 00 00 00 00 00 00"><20_2 arg="10" /><anim id="Smiling" target="actor" targetSpec="" /><20_2 arg="9" />只要摆上一件类似于
<tag a="125" b="0" arg="0x0" />的家具，<delay20 />
房间就会变成度假风呢～<pageBreak /><20_3 arg="6" /><20_3 arg="3" />心情也能变得慵懒闲适，
就像在度假村游玩一样～<tag a="110" b="6" />。</message>
	<message label="008" attrib="00 00 00 00 00 00 00 00"><20_2 arg="10" /><20_2 arg="9" />摆放着<tag a="125" b="0" arg="0x0" />……<delay20 />
<tag a="110" b="4" />，<delay20 />
你是在办公吗～？<pageBreak /><20_3 arg="6" /><20_3 arg="3" />虽然工作很重要，<delay20 />
<anim id="Restless" target="actor" targetSpec="" />但你也要留出时间<delay20 />
陪我一起玩哦～<tag a="110" b="6" />。</message>
	<message label="009" attrib="00 00 00 00 00 00 00 00"><20_2 arg="10" /><anim id="Smiling" target="actor" targetSpec="" /><20_2 arg="9" /><tag a="125" b="0" arg="0x0" /><delay20 />
看起来好酷啊～！<delay frames="40" />
<anim id="Nodding" target="actor" targetSpec="" />很符合在这里生活的感觉～<pageBreak /><20_3 arg="6" /><20_3 arg="3" />圆木不加工直接使用，<delay20 />
<anim id="Love" target="actor" targetSpec="" />有一种野性的魅力～<tag a="110" b="6" />。</message>
	<message label="010" attrib="00 00 00 00 00 00 00 00"><20_2 arg="10" /><anim id="Smiling" target="actor" targetSpec="" /><20_2 arg="9" /><tag a="125" b="0" arg="0x0" /><delay8 />这样的东西<delay20 />
被叫做“可爱”吧？<delay frames="40" />
那就是“惹人怜爱”的意思，对吧～？<pageBreak /><20_3 arg="6" /><20_3 arg="3" />既然你喜欢可爱的东西，<delay20 />
<anim id="Blushing" target="actor" targetSpec="" />那你是不是也很喜欢我呢～？<tag a="110" b="6" />。</message>
	<message label="011" attrib="00 00 00 00 00 00 00 00"><20_2 arg="10" /><anim id="Eh" target="actor" targetSpec="" /><20_2 arg="9" /><tag a="125" b="0" arg="0x0" /><delay20 />
是用<tag a="110" b="32" />上种的水果做成的吗？！<pageBreak /><anim id="Love" target="actor" targetSpec="" />嗯～<delay20 />这么一说真的好香啊～<delay frames="70" />
<20_3 arg="6" /><20_3 arg="3" />闻着这么香的味道，<delay20 />
<anim id="Laughing" target="actor" targetSpec="" />可能会忍不住咬上去呢～<tag a="110" b="6" />。<anim id="FaintSmile" target="actor" targetSpec="" /></message>
	<message label="012" attrib="00 00 00 00 00 00 00 00"><20_2 arg="10" /><anim id="Nodding" target="actor" targetSpec="" /><tag a="110" b="4" />～<delay20 />
<20_2 arg="9" />你很喜欢<tag a="125" b="0" arg="0x0" /><delay20 />
这样的风格吗～？<pageBreak /><20_3 arg="6" /><20_3 arg="3" /><anim id="FaintSmile" target="actor" targetSpec="" />这类家具放在房间里，<delay20 />
总让人有一种穿越时空的错觉，<delay20 />
<anim id="Greeting" target="actor" targetSpec="" />很有意思呢～<tag a="110" b="6" />。</message>
	<message label="013" attrib="00 00 00 00 00 00 00 00"><20_2 arg="10" /><anim id="Smiling" target="actor" targetSpec="" /><tag a="125" b="0" arg="0x0" /><20_2 arg="9" /><delay20 />
只是摆在房间里，<delay20 />
就会让人觉得很兴奋呢～<pageBreak /><20_3 arg="6" /><20_3 arg="3" /><anim id="HappyDance" target="actor" targetSpec="" />让我<delay20 />盯着它看一整天，<delay20 />
我都不会腻呢～<tag a="110" b="6" />。</message>
	<message label="014" attrib="00 00 00 00 00 00 00 00"><20_2 arg="10" /><anim id="Smiling" target="actor" targetSpec="" /><20_2 arg="9" /><tag a="125" b="0" arg="0x0" /><delay20 />
是用真的贝壳做成的吧～！<delay frames="40" />
<20_3 arg="6" /><20_3 arg="3" /><anim id="BigSmile" target="actor" targetSpec="" />闻起来有大海的味道呢～<tag a="110" b="6" />。<delay8 /><anim id="FaintSmile" target="actor" targetSpec="" /></message>
	<message label="015" attrib="00 00 00 00 00 00 00 00"><20_2 arg="10" /><anim id="Smiling" target="actor" targetSpec="" /><tag a="125" b="0" arg="0x0" /><20_2 arg="9" /><delay20 />
采用木与铁相结合的设计，<delay20 />
感觉好酷啊～！<pageBreak /><20_3 arg="6" /><20_3 arg="3" /><anim id="Nodding" target="actor" targetSpec="" />光是看看你房间的布置，<delay20 />
<delay8 />就能看出<tag a="110" b="4" />，<delay8 />
<anim id="Greeting" target="actor" targetSpec="" />你非常<delay8 />有品味呢～<tag a="110" b="6" />。</message>
	<message label="017" attrib="00 00 00 00 00 00 00 00"><20_2 arg="10" /><anim id="Smiling" target="actor" targetSpec="" /><tag a="125" b="0" arg="0x0" />，<20_2 arg="9" /><delay8 />
圆圆的，五颜六色的，<delay20 />放在那里就让人感觉
整个房间都明亮了起来，真不可思议啊～<pageBreak /><20_3 arg="6" /><20_3 arg="3" /><anim id="Confused" target="actor" targetSpec="" />不过，<delay8 />也会让人提心吊胆的～<delay frames="50" />
<anim id="ShyBoy" target="actor" targetSpec="" />因为<delay8 />它们看起来，<delay20 />
只要轻轻碰一下就会碎掉呢～<tag a="110" b="6" />。</message>
	<message label="018" attrib="00 00 00 00 00 00 00 00"><20_2 arg="10" /><20_2 arg="9" />这<tag a="125" b="0" arg="0x0" />，<delay20 />
<anim id="Hello" target="actor" targetSpec="" />难道是你妈妈亲手制作的？<pageBreak /><20_3 arg="6" /><20_3 arg="3" /><anim id="FaintSmile" target="actor" targetSpec="" />嘻嘻，<delay20 />真好啊～<delay frames="40" />
<anim id="Blushing" target="actor" targetSpec="" />我要不要也去拜托我的妈妈<delay20 />
帮我制作些东西呢～？<tag a="110" b="6" />。</message>
	<message label="019" attrib="00 00 00 00 00 00 00 00"><20_2 arg="10" /><20_2 arg="9" />在房间里摆放了
<tag a="125" b="0" arg="0x0" /><tag a="110" b="0" /><delay frames="40" />
<anim id="Hello" target="actor" targetSpec="" />你应该对宇宙很感兴趣吧？<pageBreak /><20_3 arg="6" /><20_3 arg="3" /><anim id="Explain" target="actor" targetSpec="" />我对宇宙<delay8 />也有一些了解呢～<delay frames="40" />
<anim id="Serious" target="actor" targetSpec="" />在宇宙中<tag a="110" b="0" /><10_4 /><anim id="BigSmile" target="actor" targetSpec="" /><delay20 />是没有空气的！<delay frames="40" />
<anim id="Blushing" target="actor" targetSpec="" />诶嘿嘿，<delay20 />是不是很厉害～！<tag a="110" b="6" />。</message>
	<message label="020" attrib="00 00 00 00 00 00 00 00"><20_2 arg="10" /><20_2 arg="9" /><anim id="Smiling" target="actor" targetSpec="" />看到<tag a="125" b="0" arg="0x0" />，<delay20 />
就会让人觉得很幸福，<delay8 />
你是不是也有这种感觉～？<pageBreak /><20_3 arg="6" /><20_3 arg="3" /><anim id="Love" target="actor" targetSpec="" />希望有一天，<delay8 />
我也能找到一位可爱的新娘～<delay frames="50" />
<anim id="Blushing" target="actor" targetSpec="" />到时候<delay8 />你也要来帮我庆祝哦～！<tag a="110" b="6" />。</message>
	<message label="021" attrib="00 00 00 00 00 00 00 00"><20_2 arg="10" /><20_2 arg="9" />有这<tag a="125" b="0" arg="0x0" />在，<delay20 />
<anim id="Nodding" target="actor" targetSpec="" />好像连房间中的空气<delay8 />
都化为海水了呢～<anim id="FaintSmile" target="actor" targetSpec="" />真不可思议～<pageBreak /><20_3 arg="6" /><20_3 arg="3" /><anim id="BigSmile" target="actor" targetSpec="" />不过，<delay8 />还好！<delay frames="40" />
<anim id="Laughing" target="actor" targetSpec="" />还是可以顺畅呼吸的～<tag a="110" b="6" />。<anim id="FaintSmile" target="actor" targetSpec="" /></message>
	<message label="022" attrib="00 00 00 00 00 00 00 00"><20_2 arg="10" /><20_2 arg="9" /><tag a="125" b="0" arg="0x0" /><delay20 />
看起来金闪闪的，<delay20 />
<anim id="Smiling" target="actor" targetSpec="" />装饰在房间里<delay8 />非常醒目呢～<pageBreak /><20_3 arg="6" /><20_3 arg="3" /><anim id="Aha" target="actor" targetSpec="" /><delay20 />真正的星星，<delay8 />
是不是也像这样闪闪发着光，<delay20 />
<anim id="Love" target="actor" targetSpec="" />所以离那么远看起来还是很漂亮～<tag a="110" b="6" />。</message>
	<message label="023" attrib="00 00 00 00 00 00 00 00"><20_2 arg="10" /><20_2 arg="9" />啊！<delay8 /><tag a="125" b="0" arg="0x0" />～<delay frames="40" />
<anim id="Hello" target="actor" targetSpec="" />这是<delay8 />从哪里弄来的呀～？<delay frames="50" />
<anim id="Shocked" target="actor" targetSpec="" />难道<tag a="110" b="0" /><pageBreak /><20_3 arg="6" /><20_3 arg="3" /><anim id="Pardon" target="actor" targetSpec="" /><tag a="110" b="4" />你<delay20 />
有当海盗的朋友吗～？！<delay frames="50" />
<anim id="HappyDance" target="actor" targetSpec="" />哇～<delay20 />真是让人羡慕～！<tag a="110" b="6" />。</message>
</msbt>