<msbt attribsize="8">
	<message label="001" attrib="00 00 0c 05 00 00 00 00"><anim id="Greeting" target="actor" targetSpec="" />Привет.<delay frames="40" /> <anim id="FaintSmile" target="actor" targetSpec="" />В такой день хорошо
ходить на прогулку, правда?<setNpcTalkChoices chatOption="0" cancelOption="1" /></message>
	<message label="002" attrib="00 00 0c 01 00 00 00 00">О<tag a="110" b="0" /> Опять мы встретились.
<tag a="50" b="3" /><tag a="110" b="5" />!<setNpcTalkChoices chatOption="0" cancelOption="1" /></message>
	<message label="003" attrib="00 00 0c 01 00 00 00 00"><anim id="Hello" target="actor" targetSpec="" />Еще раз привет.<delay frames="40" /><delay20 /> <anim id="Greeting" target="actor" targetSpec="" />Мы с тобой
сегодня не разлей вода!<setNpcTalkChoices chatOption="0" cancelOption="1" /></message>
	<message label="004" attrib="00 00 0c 01 00 00 00 00"><anim id="Eh" target="actor" targetSpec="" />О<tag a="110" b="0" /> <delay frames="40" /><anim id="FaintSmile" target="actor" targetSpec="" />Мы сегодня постоянно
встречаемся.<setNpcTalkChoices chatOption="0" cancelOption="1" /></message>
	<message label="005" attrib="00 00 0c 01 00 00 00 00"><anim id="Greeting" target="actor" targetSpec="" />Слушай<tag a="110" b="0" /> По-моему, я тебя сегодня
уже много раз видел.<delay20 /> <delay20 />Или мне
кажется?<setNpcTalkChoices chatOption="0" cancelOption="1" /></message>
</msbt>