<msbt attribsize="8">
	<message label="001" attrib="00 00 00 28 00 00 00 00"><anim id="HappyDance" target="actor" targetSpec="" />Ура!<delay8 /> Сегодня Хэллоуин!<delay8 />
<anim id="Shaking" target="actor" targetSpec="" />Я прямо трясусь от радости!<anim id="EmotEnd" target="actor" targetSpec="" /><pageBreak />Ну, или это я с утра конфет
объелась. От них тоже бывает
такой эффект! <tag a="50" b="3" /><tag a="110" b="6" />!</message>
	<message label="002" attrib="00 00 00 28 00 00 00 00"><anim id="Grin" target="actor" targetSpec="" />Вот и Хэллоуин!<delay20 /> День жутких
сюрпризов<tag a="110" b="0" /><delay40 /> <anim id="Surprised" target="actor" targetSpec="" />Призраки и монстры
вот-вот выскочат из укрытия!<pageBreak /><anim id="Explain" target="actor" targetSpec="" />Надеюсь, что вовремя выскочат.<delay20 />
Мне позже нужна подтанцовка,
<anim id="EmotEnd" target="actor" targetSpec="" />а хореография там не из легких!</message>
	<message label="003" attrib="00 00 00 28 00 00 00 00"><anim id="Cheering" target="actor" targetSpec="" />Ура-а!<delay20 /> Жду не дождусь вечера!<delay20 />
<anim id="EmotEnd" target="actor" targetSpec="" />Чую,<delay20 /> в этом году <anim id="EmotEnd" target="actor" targetSpec="" />вечеринка будет
просто огонь!</message>
	<message label="004" attrib="00 00 00 27 00 00 00 00"><anim id="Cheering" target="actor" targetSpec="" />♪ «Сладость или гадость!<delay8 /> Хэллоуин
нам в радость!» ♪<anim id="EmotEnd" target="actor" targetSpec="" /><delay40 /> <anim id="Explain" target="actor" targetSpec="" />Мой новый
мегахит с битбоксом!<anim id="EmotEnd" target="actor" targetSpec="" /><pageBreak /><anim id="BigSmile" target="actor" targetSpec="" />Я собираюсь ввести на Хэллоуин
новую традицию!<delay20 /> <anim id="Nodding" target="actor" targetSpec="" />Сегодня у нее
явно есть все шансы. <tag a="50" b="3" /><tag a="110" b="6" />!</message>
	<message label="005" attrib="00 00 00 27 00 00 00 00">Как твой костюм, уже готов?<delay20 />
<anim id="BigSmile" target="actor" targetSpec="" />Мой готов!<delay20 /> В этом году я сама себя
превзошла.<delay20 /> <anim id="Grin" target="actor" targetSpec="" />Даже завидую себе!</message>
	<message label="006" attrib="00 00 00 27 00 00 00 00"><anim id="Frantic" target="actor" targetSpec="" />Событие месяца<delay20 /> почти наступило!<delay20 />
Если ты не успел<gender2 m="" f="а" /> подготовиться,
<tag a="110" b="3" />, времени мало!<pageBreak /><anim id="Explain" target="actor" targetSpec="" />Только помни: <delay8 />главное — это
кон<delay8 />фе<delay8 />ты! Без них тебе не отбиться
от розыгрышей!<pageBreak /><anim id="Restless" target="actor" targetSpec="" />Я-то хорошенько запаслась, меня
врасплох не заст<tag a="110" b="0" /><delay40 /> <anim id="Surprised" target="actor" targetSpec="" />Это еще что?!<delay20 />
Дыра?!<delay8 /> Все конфеты вывалились!<pageBreak /><anim id="TakenAback" target="actor" targetSpec="" />Да, такая шутка вполне в духе
Хэллоуина.<delay20 /> Я сама себя разыграла!
<anim id="BigSmile" target="actor" targetSpec="" />Обалдеть! <tag a="50" b="3" /><tag a="110" b="6" />!</message>
	<message label="100" attrib="00 00 00 00 00 00 00 00">Мне это мерещится<tag a="110" b="0" /><anim id="Silent" target="actor" targetSpec="" /> или и в самом
деле много где повылезали тыквы?<pageBreak />Атмосфера<tag a="110" b="0" /><anim id="Aha" target="actor" targetSpec="" /> вполне себе
хэллоуинская!<delay20 /> Пойду впитывать
позитивные тыквенные вибрации!</message>
	<message label="101" attrib="00 00 00 00 00 00 00 00"><anim id="Serious" target="actor" targetSpec="" />Ты это видел<gender2 m="" f="а" />?<delay20 /> <anim id="BigSmile" target="actor" targetSpec="" />Хэллоуин
понемногу захватывает остров
<tag a="110" b="8" />!<pageBreak />Кто-то тут разошелся и все украсил!
<delay20 /><anim id="Negative" target="actor" targetSpec="" />Но как этот кто-то посмел<anim id="Worried" target="actor" targetSpec="" /> со мной
не посоветоваться?!</message>
	<message label="102" attrib="00 00 00 00 00 00 00 00"><anim id="BigSmile" target="actor" targetSpec="" />Ты только посмотри!<delay20 /> Эти тыквы
<anim id="SmugFace" target="actor" targetSpec="" />весь остров заполонили!<pageBreak /><anim id="ColdChill" target="actor" targetSpec="" />Дух Хэллоуина витает над нами<tag a="110" b="0" /><delay40 />
А это значит, <anim id="Aha" target="actor" targetSpec="" />что мой коварный
план удался! <anim id="Laughing" target="actor" targetSpec="" />Хи-и-хи-хи!!</message>
	<message label="103" attrib="00 00 00 00 00 00 00 00"><anim id="HappyFlower" target="actor" targetSpec="" />Тыквы!<delay20 /> Куда ни ткни, везде эти
тыквы! <delay8 />Шикарно!<pageBreak /><anim id="Serious" target="actor" targetSpec="" />Рыцари Тыквенного ордена<delay8 /> уже
среди нас!<delay8 /> <anim id="Surprised" target="actor" targetSpec="" />Бойся этих коренастых
служителей ужаса!<pageBreak />Уф-ф, мне будет этого не хватать.
Не каждый день можно такие
странности выкрикивать.<delay20 />
<anim id="Sighing" target="actor" targetSpec="" />Жаль, что Хэллоуин у нас не
весь год.</message>
</msbt>