<msbt attribsize="8">
	<message label="003" attrib="00 00 02 00 00 00 00 00"><anim id="Explain" target="actor" targetSpec="" />Ho letto un articolo incentrato
su un insetto très interessante:
<tag a="50" b="1" /><tag a="125" b="2" arg="0xcd00" />.
<anim id="Nodding" target="actor" targetSpec="" />È davvero incroyable! <delay8 />E veloce,
anche<tag a="110" b="0" /> <anim id="Worried" target="actor" targetSpec="" />Non sono ancora riuscita a
catturarne un esemplare.</message>
	<message label="003_a" attrib="00 00 00 00 00 00 00 00">Lascia fare a me!</message>
	<message label="003_b" attrib="00 00 00 00 00 00 00 00"><anim id="EmotEnd" target="actor" targetSpec="" />Non mollare!</message>
	<message label="004" attrib="00 00 02 00 00 00 00 00"><anim id="Explain" target="actor" targetSpec="" />Ho letto un libro sugli insetti rari
e vorrei tanto esaminare da vicino
<tag a="50" b="2" /><tag a="125" b="2" arg="0xcd00" />.
<anim id="Sighing" target="actor" targetSpec="" />Purtroppo è un tipo di insetto che
non si lascia catturare per nulla
facilmente<tag a="110" b="0" /></message>
	<message label="004_a" attrib="00 00 00 00 00 00 00 00"><anim id="EmotEnd" target="player" targetSpec="" />Vuoi che ti aiuti?</message>
	<message label="004_b" attrib="00 00 00 00 00 00 00 00"><anim id="EmotEnd" target="actor" targetSpec="" />Continua a provarci!</message>
	<message label="008" attrib="00 00 02 00 00 00 00 00"><anim id="Explain" target="actor" targetSpec="" />Di recente, ho visto la foto di <tag a="50" b="2" /><tag a="125" b="3" arg="0xcd00" /> in un manuale di pesca.<pageBreak /><anim id="Nodding" target="actor" targetSpec="" />Si tratta di esemplari meravigliosi<delay20 />
<anim id="Worried" target="actor" targetSpec="" />che però non si trovano facilmente
qui in giro.
<anim id="Frantic" target="actor" targetSpec="" />Sarebbe così bello se riuscissi
a catturarne <tag a="50" b="17" arg="0x15 0xcd00 0x6 0x75 0x6e 0x6f 0x6 0x75 0x6e 0x61 0x0" />.</message>
	<message label="008_a" attrib="00 00 00 00 00 00 00 00"><anim id="EmotEnd" target="player" targetSpec="" />Ti do una mano io.</message>
	<message label="008_b" attrib="00 00 00 00 00 00 00 00"><anim id="EmotEnd" target="actor" targetSpec="" />Non mollare!</message>
	<message label="009" attrib="00 00 02 00 00 00 00 00"><anim id="Explain" target="actor" targetSpec="" /><tag a="50" b="3" /><tag a="50" b="1" /><tag a="125" b="3" arg="0xcd00" /><tag a="110" b="0" /><delay8 />
Ne hai sentito parlare? È una specie
che io ho scoperto poco tempo fa.
<anim id="Frantic" target="actor" targetSpec="" />Da allora sogno di catturarne <tag a="50" b="17" arg="0x15 0xcd00 0x6 0x75 0x6e 0x6f 0x6 0x75 0x6e 0x61 0x0" /><tag a="110" b="0" />
<delay20 /><anim id="Sighing" target="actor" targetSpec="" />Purtroppo con la mia canna è
impossibile.</message>
	<message label="009_a" attrib="00 00 00 00 00 00 00 00"><anim id="EmotEnd" target="player" targetSpec="" />Posso aiutarti?</message>
	<message label="009_b" attrib="00 00 00 00 00 00 00 00"><anim id="EmotEnd" target="actor" targetSpec="" />Prova ancora.</message>
	<message label="011" attrib="00 00 00 00 00 00 00 00"><anim id="HappyDance" target="actor" targetSpec="" />Oh, merci, merci, merci! <delay20 /><anim id="FaintSmile" target="actor" targetSpec="" />Spero tanto
che ce la farai!</message>
	<message label="012" attrib="00 00 00 00 00 00 00 00"><anim id="Aha" target="actor" targetSpec="" />Oh, lo faresti davvero? <delay20 /><anim id="FaintSmile" target="actor" targetSpec="" />Merci e buona
fortuna, allora!</message>
	<message label="013" attrib="00 00 00 00 00 00 00 00"><anim id="Aha" target="actor" targetSpec="" />Lo faresti davvero per me?<delay20 />
<anim id="HappyDance" target="actor" targetSpec="" />Uau! <delay8 />Merci, merci, merci!</message>
	<message label="014" attrib="00 00 00 00 00 00 00 00"><anim id="BigSmile" target="actor" targetSpec="" />Oh, non immagini nemmeno quanto
mi faresti felice! <delay8 />Non vedo l'ora!</message>
	<message label="015" attrib="00 00 00 00 00 00 00 00"><anim id="Worried" target="actor" targetSpec="" />Merci del sostegno, però è così
frustrante.</message>
	<message label="016" attrib="00 00 00 00 00 00 00 00"><anim id="Sighing" target="actor" targetSpec="" />Merci, continuerò a provare.</message>
	<message label="017" attrib="00 00 00 00 00 00 00 00"><anim id="Nodding" target="actor" targetSpec="" />Merci, seguirò il tuo consiglio.<delay20 />
<anim id="FaintSmile" target="actor" targetSpec="" />Prima o poi ce la farò!</message>
	<message label="018" attrib="00 00 00 00 00 00 00 00"><anim id="FaintSmile" target="actor" targetSpec="" />Merci per l'incoraggiamento! <delay20 />Terrò
duro e forse prima o poi la fortuna
mi sorriderà!</message>
	<message label="021" attrib="00 00 02 00 00 00 00 00"><anim id="Thinking" target="actor" targetSpec="" />Mi sono sempre chiesta come fanno
gli scarabei a volare<tag a="110" b="0" /> Sono pesanti
e hanno corna così grandi.
<anim id="AbsentMindedness" target="actor" targetSpec="" />Sarebbe bello vederne uno volare
per cercare di capire come fa.<pageBreak /><anim id="Aha" target="actor" targetSpec="" />Oh, <delay8 />forse tu puoi darmi una zampa?<delay20 />
<anim id="FaintSmile" target="actor" targetSpec="" />Potresti catturare uno scarabeo per
me? <delay20 />Va bene uno di qualsiasi tipo.</message>
	<message label="021_a" attrib="00 00 00 00 00 00 00 00">Lascia fare a me!
OK!
Certo!</message>
	<message label="021_b" attrib="00 00 00 00 00 00 00 00"><anim id="EmotEnd" target="player" targetSpec="" />Scusa, è che ora...
Adesso non posso.
Mi spiace, ma... no.</message>
	<message label="022" attrib="00 00 02 00 00 00 00 00"><anim id="Nodding" target="actor" targetSpec="" />Le mandibole dei coleotteri sono
adoraaabili, n'est-ce pas?<pageBreak /><anim id="Worried" target="actor" targetSpec="" />Vorrei tanto esaminare un esemplare
da vicino, ma per me è impossibile
catturarne uno.
<anim id="QuestionMark" target="actor" targetSpec="" />Tu che dici, <tag a="110" b="3" />? <delay20 />Ti
andrebbe di prendere un coleottero
per me?</message>
	<message label="022_a" attrib="00 00 00 00 00 00 00 00">Lascia fare a me!
OK!
Certo!</message>
	<message label="022_b" attrib="00 00 00 00 00 00 00 00"><anim id="EmotEnd" target="player" targetSpec="" />Scusa, è che ora...
Adesso non posso.
Mi spiace, ma... no.</message>
	<message label="023" attrib="00 00 02 00 00 00 00 00"><anim id="Eh" target="actor" targetSpec="" />Capita anche a te che il suono delle
cicale ti faccia pensare all'estate?<delay20 />
<anim id="HappyFlower" target="actor" targetSpec="" />Io lo trovo così melodioso e allegro!
<anim id="Explain" target="actor" targetSpec="" />Ho provato spesso a catturarle per
studiare il loro modo di cantare, <delay20 /><anim id="OhGeez" target="actor" targetSpec="" />ma
scappano sempre quando mi vedono.
<anim id="Hesitate" target="actor" targetSpec="" />Pensi che tu potresti prendere una
cicala per me, <tag a="110" b="3" />?</message>
	<message label="023_a" attrib="00 00 00 00 00 00 00 00">Lascia fare a me!
OK!
Certo!</message>
	<message label="023_b" attrib="00 00 00 00 00 00 00 00"><anim id="EmotEnd" target="player" targetSpec="" />Scusa, è che ora...
Adesso non posso.
Mi spiace, ma... no.</message>
	<message label="025" attrib="00 00 02 00 00 00 00 00"><anim id="Hesitate" target="actor" targetSpec="" />Vorrei chiederti un favore,
<tag a="110" b="3" /><tag a="110" b="0" /><pageBreak /><anim id="Explain" target="actor" targetSpec="" />Sto imparando a creare delle piccole
figure di zucchero per decorare torte
e dolci in genere.
<anim id="AbsentMindedness" target="actor" targetSpec="" />Adooorerei creare una farfalla,
ma prima vorrei osservarne una
da vicino<tag a="110" b="0" />
<anim id="Hesitate" target="actor" targetSpec="" />Mi porteresti una farfalla che abbia
voglia di fare da modella per i miei
dolci? <delay20 /><anim id="FaintSmile" target="actor" targetSpec="" />Qualsiasi tipo va bene!</message>
	<message label="025_a" attrib="00 00 00 00 00 00 00 00">Lascia fare a me!
OK!
Certo!</message>
	<message label="025_b" attrib="00 00 00 00 00 00 00 00"><anim id="EmotEnd" target="player" targetSpec="" />Scusa, è che ora...
Adesso non posso.
Mi spiace, ma... no.</message>
	<message label="026" attrib="00 00 02 00 00 00 00 00"><anim id="Greeting" target="actor" targetSpec="" />Le libellule sono così affascinanti.<delay20 />
<anim id="FaintSmile" target="actor" targetSpec="" />Pensa che possono restare ferme
in aria volando per un minuto!
<anim id="Thinking" target="actor" targetSpec="" />Non so come facciano a coordinare
quattro ali alla volta<tag a="110" b="0" /><pageBreak /><anim id="AbsentMindedness" target="actor" targetSpec="" />Mi piacerebbe tanto studiarne una
da vicino<tag a="110" b="0" /> <delay20 /><anim id="QuestionMark" target="actor" targetSpec="" />Non è che cattureresti
una libellula per me?</message>
	<message label="026_a" attrib="00 00 00 00 00 00 00 00">Lascia fare a me!
OK!
Certo!</message>
	<message label="026_b" attrib="00 00 00 00 00 00 00 00"><anim id="EmotEnd" target="player" targetSpec="" />Scusa, è che ora...
Adesso non posso.
Mi spiace, ma... no.</message>
	<message label="027" attrib="00 00 02 00 00 00 00 00"><anim id="Explain" target="actor" targetSpec="" />Sto facendo una ricerca sugli insetti
che si posano allegramente di fiore
in fiore.
<anim id="Worried" target="actor" targetSpec="" />Però non sono riuscita a prenderne
nemmeno uno.<pageBreak /><anim id="Hesitate" target="actor" targetSpec="" />Se vedi un insetto su un fiore,
potresti catturarlo per me,
<tag a="110" b="3" />?</message>
	<message label="027_a" attrib="00 00 00 00 00 00 00 00">Lascia fare a me!
OK!
Certo!</message>
	<message label="027_b" attrib="00 00 00 00 00 00 00 00"><anim id="EmotEnd" target="player" targetSpec="" />Scusa, è che ora...
Adesso non posso.
Mi spiace, ma... no.</message>
	<message label="028" attrib="00 00 02 00 00 00 00 00"><anim id="Explain" target="actor" targetSpec="" />Ho letto che le termiti e altri insetti
simili amano il legno vecchio, come
quello dei ceppi d'albero<tag a="110" b="0" />
<anim id="AbsentMindedness" target="actor" targetSpec="" />Mi chiedo come facciano a trovare
i ceppi<tag a="110" b="0" /> <delay20 /><anim id="Thinking" target="actor" targetSpec="" />Forse ne percepiscono
l'odore con le loro antenne?
<anim id="Nodding" target="actor" targetSpec="" />Devo scoprirlo!<pageBreak /><anim id="Hesitate" target="actor" targetSpec="" />Senti, se vedi un insetto appoggiato
a un ceppo d'albero, <delay8 />potresti magari
prenderlo e portarmelo subito?</message>
	<message label="028_a" attrib="00 00 00 00 00 00 00 00">Lascia fare a me!
OK!
Certo!</message>
	<message label="028_b" attrib="00 00 00 00 00 00 00 00"><anim id="EmotEnd" target="player" targetSpec="" />Scusa, è che ora...
Adesso non posso.
Mi spiace, ma... no.</message>
	<message label="031" attrib="00 00 02 00 00 00 00 00"><anim id="Explain" target="actor" targetSpec="" />Medito spesso sulle differenze tra
i pesci di mare e quelli d'acqua
dolce<tag a="110" b="0" />
<anim id="AbsentMindedness" target="actor" targetSpec="" />Una volta ho visto un pesce risalire
la corrente di un fiume e mi sono
chiesta se ciò lo rendesse più forte.
<anim id="Eh" target="actor" targetSpec="" />Oh! <delay20 /><anim id="Hesitate" target="actor" targetSpec="" />Pensi che potresti catturarmi
un qualsiasi pesce d'acqua dolce
per poterlo studiare da vicino?</message>
	<message label="031_a" attrib="00 00 00 00 00 00 00 00">Lascia fare a me!
OK!
Certo!</message>
	<message label="031_b" attrib="00 00 00 00 00 00 00 00"><anim id="EmotEnd" target="player" targetSpec="" />Scusa, è che ora...
Adesso non posso.
Mi spiace, ma... no.</message>
	<message label="032" attrib="00 00 02 00 00 00 00 00"><anim id="Explain" target="actor" targetSpec="" />Ultimamente ho riflettuto molto
sulle differenze tra i pesci di mare
e quelli d'acqua dolce<tag a="110" b="0" />
<anim id="Thinking" target="actor" targetSpec="" />Adooorerei studiare un pesce
di mare<tag a="110" b="0" /> <delay20 /><anim id="Hesitate" target="actor" targetSpec="" />Saresti così gentile
da prenderne uno per me?</message>
	<message label="032_a" attrib="00 00 00 00 00 00 00 00">Lascia fare a me!
OK!
Certo!</message>
	<message label="032_b" attrib="00 00 00 00 00 00 00 00"><anim id="EmotEnd" target="player" targetSpec="" />Scusa, è che ora...
Adesso non posso.
Mi spiace, ma... no.</message>
	<message label="101" attrib="00 00 02 00 00 00 00 00"><anim id="Aha" target="actor" targetSpec="" />Ho bisogno che tu mi faccia un
grosso favore! <delay20 /><anim id="Worried" target="actor" targetSpec="" />Tu sei bravissim<gender2 m="o" f="a" />
a catturare insetti, no?
<anim id="Hesitate" target="actor" targetSpec="" />Saresti così gentile da prendere <tag a="50" b="2" /><tag a="125" b="2" arg="0xcd00" /> per me?</message>
	<message label="101_a" attrib="00 00 00 00 00 00 00 00">Certo!</message>
	<message label="101_b" attrib="00 00 00 00 00 00 00 00">Adesso non posso...</message>
	<message label="102" attrib="00 00 02 00 00 00 00 00"><anim id="Eh" target="actor" targetSpec="" />Aiutamiii, <tag a="110" b="3" />, <delay8 />ti prego! <delay20 /><anim id="Worried" target="actor" targetSpec="" />Non riesco a prendere <tag a="50" b="2" /><tag a="125" b="2" arg="0xcd00" /><tag a="110" b="0" /></message>
	<message label="102_a" attrib="00 00 00 00 00 00 00 00">Ci penso io!</message>
	<message label="102_b" attrib="00 00 00 00 00 00 00 00"><anim id="EmotEnd" target="actor" targetSpec="" />Ce la puoi fare!</message>
	<message label="103" attrib="00 00 00 00 00 00 00 00"><anim id="BigSmile" target="actor" targetSpec="" />Merci, <tag a="110" b="3" />! <delay8 />Sono sicura che ce la farai. <delay20 /><anim id="FaintSmile" target="actor" targetSpec="" />Non vedo l'ora, <tag a="110" b="5" />!</message>
	<message label="104" attrib="00 00 00 00 00 00 00 00"><anim id="Worried" target="actor" targetSpec="" />Oh, non volevo essere invadente,
<delay8 />scusa.<delay20 /> <anim id="FaintSmile" target="actor" targetSpec="" />Forse potrai aiutarmi un'altra
volta, <tag a="110" b="6" />.</message>
	<message label="105" attrib="00 00 00 00 00 00 00 00"><anim id="Aha" target="actor" targetSpec="" />Davvero, <delay8 />ci pensi tu? <delay20 /><anim id="FaintSmile" target="actor" targetSpec="" />Che offerta
generosa. <delay8 />Merci!</message>
	<message label="106" attrib="00 00 00 00 00 00 00 00">Merci! <anim id="FaintSmile" target="actor" targetSpec="" />Non mi darò per vinta,
prenderò nelle zampe il mio
destino.</message>
	<message label="201" attrib="00 00 02 00 00 00 00 00"><anim id="Worried" target="actor" targetSpec="" />Devi aiutarmi, per favooore! <delay20 />Vorrei
catturare un pesce, <delay8 />ma maneggiare
una canna non fa pour moi.
<anim id="Hesitate" target="actor" targetSpec="" />Mi faresti il favore di catturare <tag a="50" b="2" /><tag a="125" b="3" arg="0xcd00" />?<delay20 /> Tu non avresti problemi, lo so!</message>
	<message label="201_a" attrib="00 00 00 00 00 00 00 00">Ma certo!</message>
	<message label="201_b" attrib="00 00 00 00 00 00 00 00">Adesso no, scusa.</message>
	<message label="202" attrib="00 00 02 00 00 00 00 00"><anim id="Eh" target="actor" targetSpec="" />Oh, <tag a="110" b="3" />! <delay20 />Puoi aiutarmi?<pageBreak /><anim id="Worried" target="actor" targetSpec="" />Non riesco proprio a catturare <tag a="50" b="2" /><tag a="125" b="3" arg="0xcd00" /><tag a="110" b="0" /> Potresti farlo tu per me?</message>
	<message label="202_a" attrib="00 00 00 00 00 00 00 00">Ci proverò.</message>
	<message label="202_b" attrib="00 00 00 00 00 00 00 00"><anim id="EmotEnd" target="actor" targetSpec="" />Non mollare!</message>
	<message label="203" attrib="00 00 00 00 00 00 00 00"><anim id="BigSmile" target="actor" targetSpec="" />Sei <gender2 m="il mio eroe" f="un'amica" />, <tag a="110" b="3" />!<delay20 /> <anim id="Smiling" target="actor" targetSpec="" />Se qualcuno può farcela, <delay8 /><gender2 m="quello" f="quella" /> sei tu.</message>
	<message label="204" attrib="00 00 00 00 00 00 00 00"><anim id="Nodding" target="actor" targetSpec="" />Capisco, <delay8 />scusa per avertelo chiesto.<delay20 />
<anim id="FaintSmile" target="actor" targetSpec="" />Sono sicura che mi aiuteresti, se
potessi.</message>
	<message label="205" attrib="00 00 00 00 00 00 00 00"><anim id="BigSmile" target="actor" targetSpec="" />Uau, <delay8 />merci, merci, merci!<delay20 /> Sapevo
di poter contare su di te.</message>
	<message label="206" attrib="00 00 00 00 00 00 00 00"><anim id="FaintSmile" target="actor" targetSpec="" />Hai ragione! <delay20 />Non devo desistere.<delay20 />
Merci per l'incoraggiamento!</message>
</msbt>